{
    "data": [
        {
            "tag": "#8YQ2PG29L",
            "name": "|Te Amo Yuri \ud83c\udf39",
            "trophies": 30736
        },
        {
            "tag": "#8LCGR9YVC",
            "name": "BrawlGod",
            "trophies": 30586
        },
        {
            "tag": "#9QCPUCVUG",
            "name": "\u0417\u0432\u0451\u0437\u0434\u043d\u044b\u0439 \u0438\u0433\u0440\u043e\u043a",
            "trophies": 29222
        },
        {
            "tag": "#YL0G2GUG",
            "name": "\u2744\ufe0fFrosty\u2744\ufe0f",
            "trophies": 28931
        },
        {
            "tag": "#8L0QJGPR0",
            "name": "\u262a\ufe0f\u26ce\u264d\ufe0f",
            "trophies": 28696
        },
        {
            "tag": "#PRC2GGGJY",
            "name": "ToXik",
            "trophies": 27956
        },
        {
            "tag": "#YULQGJGQ",
            "name": "Angel \ud83d\udc7c\ud83d\udc7c\ud83d\udc7c",
            "trophies": 27411
        },
        {
            "tag": "#CQ8JLP08",
            "name": "R\u0366\u0325a\u0366\u0325g\u0366\u0325e\u0366\u0325",
            "trophies": 27244
        },
        {
            "tag": "#2VGJUQU2",
            "name": "KilahB",
            "trophies": 26938
        },
        {
            "tag": "#9L8L0CGG",
            "name": "asian trash can",
            "trophies": 26398
        },
        {
            "tag": "#20G80C0R",
            "name": "ToxicVR",
            "trophies": 26173
        },
        {
            "tag": "#9VC2PCYQ",
            "name": "CR7\ud83d\ude0eHeheheSiuu",
            "trophies": 26113
        },
        {
            "tag": "#22GYGC9QJ",
            "name": "MonkeymanTTV",
            "trophies": 26032
        },
        {
            "tag": "#RYJLRJ02",
            "name": "biglele",
            "trophies": 25846
        },
        {
            "tag": "#2YQGG89J0",
            "name": "fearthedear",
            "trophies": 25657
        },
        {
            "tag": "#PUCRGV802",
            "name": "Dr. Strange",
            "trophies": 24907
        },
        {
            "tag": "#9PP2GY00J",
            "name": "bodybuilder",
            "trophies": 24894
        },
        {
            "tag": "#99PVU2CPY",
            "name": "squidboi",
            "trophies": 24378
        },
        {
            "tag": "#82VJJQCGR",
            "name": "NOICEXD",
            "trophies": 24292
        },
        {
            "tag": "#VYC08LJV",
            "name": "Frenchy",
            "trophies": 24190
        },
        {
            "tag": "#YUGYY00LV",
            "name": "moumoney",
            "trophies": 23463
        },
        {
            "tag": "#PCUQG828",
            "name": "BlueBlaze03",
            "trophies": 23327
        },
        {
            "tag": "#20UPLGYJC",
            "name": "niceshirtguy",
            "trophies": 22811
        },
        {
            "tag": "#LYG2P02U8",
            "name": "oopadoo",
            "trophies": 22304
        },
        {
            "tag": "#2Q90VQR0L",
            "name": "@SRALEXIG",
            "trophies": 21739
        },
        {
            "tag": "#2JJ0YPYJC",
            "name": "\ud83c\udf44N\u0e19gget\ud83c\udf44",
            "trophies": 21226
        },
        {
            "tag": "#YGP8PC2L2",
            "name": "Samm",
            "trophies": 21216
        },
        {
            "tag": "#G9VJVQCG",
            "name": "angry pumkin",
            "trophies": 20226
        },
        {
            "tag": "#Y2PUYCUC8",
            "name": "\ud83c\udde6\ud83c\uddf1 LIRI \ud83c\udde6\ud83c\uddf1",
            "trophies": 18427
        },
        {
            "tag": "#LYGJ2LUPC",
            "name": "SUPPort",
            "trophies": 13748
        }
    ]
}